[{"id":"44481","lat":41.8962818,"lon":15.0770609,"name":"NUOVA CLITERNIA TAMOIL","brand":"Tamoil","address":"Via Madonna Grande  86042, CAMPOMARINO, CB","prices":[{"type":"petrol","price":1.829,"self":true,"updatedAt":"24/06/2026 07:19:40"},{"type":"diesel","price":1.939,"self":true,"updatedAt":"24/06/2026 07:19:40"}]},{"id":"49233","lat":41.94975760507629,"lon":15.025386214256287,"name":"CAMPOMARINO","brand":"Pompe Bianche","address":"S.P. 40 ADRIATICA C/DA FAVOTITA  86042, CAMPOMARINO, CB","prices":[{"type":"petrol","price":1.839,"self":true,"updatedAt":"24/06/2026 11:56:06"},{"type":"diesel","price":1.929,"self":true,"updatedAt":"24/06/2026 11:56:06"}]},{"id":"60247","lat":41.9562688,"lon":15.034344,"name":"CAMPOMARINO","brand":"Pompe Bianche","address":"SS16 555  86042, CAMPOMARINO, CB","prices":[{"type":"petrol","price":1.796,"self":true,"updatedAt":"25/06/2026 00:25:54"},{"type":"diesel","price":1.875,"self":true,"updatedAt":"25/06/2026 00:25:54"}]},{"id":"63201","lat":41.9583015,"lon":15.0388259,"name":"IP CAMPOMARINO LIDO","brand":"Api-Ip","address":"SS16 KM 554+697 CAMPOMARINO  86042, CAMPOMARINO, CB","prices":[{"type":"petrol","price":1.839,"self":true,"updatedAt":"22/06/2026 11:41:36"},{"type":"diesel","price":1.939,"self":true,"updatedAt":"22/06/2026 11:41:36"}]},{"id":"5759","lat":41.95202741400315,"lon":15.04936623545791,"name":"PETROLADRIATICASNC","brand":"Tamoil","address":"Statale 16 Adriatica, Km. 552+016, dir. sud - 86042, CAMPOMARINO, CB","prices":[{"type":"petrol","price":1.819,"self":true,"updatedAt":"25/06/2026 01:22:04"},{"type":"diesel","price":1.899,"self":true,"updatedAt":"25/06/2026 01:22:04"},{"type":"lpg","price":0.729,"self":false,"updatedAt":"25/06/2026 00:52:19"}]},{"id":"32822","lat":41.95859334823048,"lon":15.03797248005867,"name":"TOTALERG","brand":"Api-Ip","address":"Statale 16 Adriatica, Km. 550+700, dir. BARI - 86042, CAMPOMARINO, CB","prices":[{"type":"petrol","price":1.829,"self":true,"updatedAt":"25/06/2026 00:23:35"},{"type":"diesel","price":1.939,"self":true,"updatedAt":"25/06/2026 00:23:35"}]},{"id":"58967","lat":41.917287,"lon":15.00953,"name":"TAMOIL PORTOCANNONE VIA GARIBALDI","brand":"Tamoil","address":"SP 40 - VIA GARIBALDI SNC 86045, PORTOCANNONE, CB","prices":[{"type":"petrol","price":1.819,"self":true,"updatedAt":"25/06/2026 07:45:42"},{"type":"diesel","price":1.919,"self":true,"updatedAt":"25/06/2026 07:45:42"}]},{"id":"30151","lat":41.87051823616412,"lon":15.01107513140414,"name":"SAN MARTINO TAMOIL","brand":"Tamoil","address":"via marina snc 86046, SAN MARTINO IN PENSILIS, CB","prices":[{"type":"petrol","price":1.829,"self":true,"updatedAt":"24/06/2026 07:17:28"},{"type":"diesel","price":1.929,"self":true,"updatedAt":"24/06/2026 07:17:28"}]},{"id":"6304","lat":41.878299507342724,"lon":15.016989399119552,"name":"Eni San Martino in Pensilis","brand":"Agip Eni","address":"CONTRADA ARENALE SNC 86046, SAN MARTINO IN PENSILIS, CB","prices":[{"type":"petrol","price":1.829,"self":true,"updatedAt":"25/06/2026 00:47:44"},{"type":"diesel","price":1.929,"self":true,"updatedAt":"25/06/2026 00:47:44"}]},{"id":"4554","lat":41.970117419836036,"lon":15.003867596387858,"name":"ECO-FUEL METANO - TERMOLI 1","brand":"ECOFUEL","address":"Contrada Pantano Alto SNC 86039, TERMOLI, CB","prices":[{"type":"methane","price":1.398,"self":false,"updatedAt":"20/06/2026 08:43:11"}]},{"id":"60817","lat":41.972233524606885,"lon":15.004119944524765,"name":"ECOFUEL-TERMOLI 2","brand":"ECOFUEL","address":"ACACIE SNC 86039, TERMOLI, CB","prices":[{"type":"petrol","price":1.818,"self":true,"updatedAt":"23/06/2026 08:22:39"},{"type":"diesel","price":1.898,"self":true,"updatedAt":"23/06/2026 08:22:39"},{"type":"methane","price":1.45,"self":false,"updatedAt":"23/06/2026 08:22:39"},{"type":"lpg","price":0.777,"self":false,"updatedAt":"23/06/2026 08:22:39"}]},{"id":"57473","lat":41.9758993,"lon":15.010568,"name":"Esso Termoli sud","brand":"Esso","address":"SS16 km 547+545  86039, TERMOLI, CB","prices":[{"type":"petrol","price":1.819,"self":true,"updatedAt":"24/06/2026 07:42:28"},{"type":"diesel","price":1.899,"self":true,"updatedAt":"24/06/2026 07:42:29"}]},{"id":"49456","lat":41.96914965983584,"lon":15.014198272635948,"name":"Interpetrol_Termoli","brand":"Interpetrol","address":"16 Adriatica, Km. 548, Nord - 86039, TERMOLI, CB","prices":[{"type":"petrol","price":1.818,"self":true,"updatedAt":"24/06/2026 12:03:27"},{"type":"diesel","price":1.888,"self":true,"updatedAt":"24/06/2026 12:03:27"},{"type":"lpg","price":0.629,"self":false,"updatedAt":"24/06/2026 12:03:26"}]},{"id":"49004","lat":41.98324563936003,"lon":15.00510303333796,"name":"PORTOBELLO AREA DI SERVIZIO TERMOLI","brand":"Pompe Bianche","address":"VIA CORSICA SNC 86039, TERMOLI, CB","prices":[{"type":"petrol","price":1.818,"self":true,"updatedAt":"25/06/2026 07:51:32"},{"type":"diesel","price":1.888,"self":true,"updatedAt":"25/06/2026 07:51:32"}]},{"id":"60530","lat":41.920647,"lon":15.15662,"name":"9315 CHIEUTI","brand":"Agip Eni","address":"VARIANTE S.S. 16 SCALO FERROVIARIO  SN, CHIEUTI, FG","prices":[{"type":"petrol","price":1.829,"self":true,"updatedAt":"24/06/2026 23:46:19"},{"type":"diesel","price":1.909,"self":true,"updatedAt":"24/06/2026 07:52:09"}]},{"id":"62739","lat":41.909773211626174,"lon":15.168052911758423,"name":"TORRE FANTINE EST","brand":"Sarni Oil","address":"Autostrada A14 BOLOGNA-BARI-TARANTO, Km. 493+500, dir. NORD - 71010, CHIEUTI, FG","prices":[{"type":"diesel","price":1.969,"self":true,"updatedAt":"24/06/2026 15:18:17"}]},{"id":"35466","lat":41.909773211626174,"lon":15.168052911758423,"name":"TORRE FANTINE EST","brand":"Sarni Oil","address":"Autostrada A14 BOLOGNA-BARI-TARANTO, Km. 493+500, dir. NORD - 71010, CHIEUTI, FG","prices":[{"type":"petrol","price":1.888,"self":true,"updatedAt":"24/06/2026 16:01:04"},{"type":"diesel","price":1.999,"self":true,"updatedAt":"24/06/2026 16:01:04"},{"type":"lpg","price":0.778,"self":false,"updatedAt":"24/06/2026 16:01:06"}]},{"id":"62726","lat":41.90867019018783,"lon":15.169573015406499,"name":"TORRE FANTINE OVEST","brand":"Sarni Oil","address":"A14 BOLOGNA-BARI-TARANTO, Km. 493,50, SUD - 71010, CHIEUTI, FG","prices":[{"type":"diesel","price":1.879,"self":true,"updatedAt":"24/06/2026 10:48:36"}]},{"id":"47640","lat":41.90867019018783,"lon":15.169573015406499,"name":"TORRE FANTINE OVEST","brand":"Sarni Oil","address":"A14 BOLOGNA-BARI-TARANTO, Km. 493,50, SUD - 71010, CHIEUTI, FG","prices":[{"type":"petrol","price":1.889,"self":true,"updatedAt":"24/06/2026 14:00:08"},{"type":"diesel","price":1.998,"self":true,"updatedAt":"24/06/2026 16:00:38"},{"type":"lpg","price":0.898,"self":false,"updatedAt":"24/06/2026 16:00:36"}]},{"id":"36629","lat":41.76268930158431,"lon":15.224760174751282,"name":"METANO SAN PAOLO","brand":"ECOFUEL","address":"Ex Strada Statale 16, Km. 35,400, dir. s.paolo di civitate  71010, SAN PAOLO DI CIVITATE, FG","prices":[{"type":"methane","price":1.35,"self":false,"updatedAt":"20/06/2026 08:43:17"}]},{"id":"19757","lat":41.830919677412766,"lon":15.174449988071046,"name":"DISTRIBUTORE DI CARBURANTI \"LOW COST\" DI DI SIRO LUIGI VINCENZO","brand":"Pompe Bianche","address":"ZONA INDUSTRIALE TRE MONTI  71010, SERRACAPRIOLA, FG","prices":[{"type":"petrol","price":1.86,"self":true,"updatedAt":"24/06/2026 11:28:31"},{"type":"diesel","price":1.94,"self":true,"updatedAt":"24/06/2026 11:28:32"}]}]