[{"id":"48005","lat":44.895064800157265,"lon":9.970075093254103,"name":"Alseno","brand":"Esso","address":"VIA ROMA SN 29010, ALSENO, PC","prices":[{"type":"petrol","price":1.879,"self":true,"updatedAt":"09/06/2026 15:41:39"},{"type":"diesel","price":1.979,"self":true,"updatedAt":"09/06/2026 15:41:39"}]},{"id":"63086","lat":44.89507228835233,"lon":9.970051645364807,"name":"ESSO - ALSENO","brand":"Esso","address":"Via Roma 447 29010, ALSENO, PC","prices":[{"type":"petrol","price":1.779,"self":true,"updatedAt":"20/06/2026 07:51:03"},{"type":"diesel","price":1.879,"self":true,"updatedAt":"20/06/2026 07:51:03"}]},{"id":"11310","lat":44.88658452059114,"lon":9.9900484085083,"name":"TOSI PIETRO","brand":"Pompe Bianche","address":"Statale 9 Via Emilia, Km. 231.6, dir. Bologna - -, ALSENO, PC","prices":[{"type":"petrol","price":1.795,"self":true,"updatedAt":"21/06/2026 23:58:09"},{"type":"diesel","price":1.875,"self":true,"updatedAt":"21/06/2026 23:58:09"}]},{"id":"11751","lat":44.96631404121732,"lon":9.849873483181,"name":"CADEO-FZ.ROVELETO VIA EMILIA SS.9 KM.245","brand":"Q8","address":"FZ.ROVELETO VIA EMILIA SS.9 KM.245 S/N 29010, CADEO, PC","prices":[{"type":"petrol","price":1.799,"self":true,"updatedAt":"20/06/2026 08:13:02"},{"type":"diesel","price":1.939,"self":true,"updatedAt":"20/06/2026 08:13:02"}]},{"id":"61309","lat":44.9720897,"lon":9.83902185,"name":"pv 12695","brand":"Agip Eni","address":"Via Emilia Parmense 8 29010, CADEO, PC","prices":[{"type":"petrol","price":1.809,"self":true,"updatedAt":"21/06/2026 23:14:02"},{"type":"diesel","price":1.919,"self":true,"updatedAt":"21/06/2026 23:14:02"}]},{"id":"49055","lat":44.91534535487377,"lon":9.789517024245917,"name":"ENI","brand":"Agip Eni","address":"VIA GIANCARLO ROSSI 1 01 29013, CARPANETO PIACENTINO, PC","prices":[{"type":"petrol","price":1.824,"self":true,"updatedAt":"22/06/2026 00:25:12"},{"type":"diesel","price":1.914,"self":true,"updatedAt":"22/06/2026 00:25:12"}]},{"id":"39534","lat":44.91086046975764,"lon":9.806775748729706,"name":"IP DI DANZINELLI EUGENIO","brand":"Api-Ip","address":"LOCALITA' CASE DRAGHI SNC 29013, CARPANETO PIACENTINO, PC","prices":[{"type":"petrol","price":1.879,"self":true,"updatedAt":"19/06/2026 09:00:20"},{"type":"diesel","price":1.969,"self":true,"updatedAt":"19/06/2026 09:00:20"}]},{"id":"51141","lat":44.85245146295033,"lon":9.875123128294945,"name":"eni","brand":"Agip Eni","address":"VIA ILLICA 21 29014, CASTELL'ARQUATO, PC","prices":[{"type":"petrol","price":1.824,"self":true,"updatedAt":"22/06/2026 06:16:06"},{"type":"diesel","price":1.914,"self":true,"updatedAt":"22/06/2026 06:16:06"}]},{"id":"49692","lat":44.858880503771445,"lon":9.883339405059814,"name":"PV 1800","brand":"Q8","address":"Via Case Sparse Castellana  29014, CASTELL'ARQUATO, PC","prices":[{"type":"petrol","price":1.819,"self":true,"updatedAt":"22/06/2026 00:50:01"},{"type":"diesel","price":1.919,"self":true,"updatedAt":"22/06/2026 00:50:01"},{"type":"lpg","price":0.799,"self":false,"updatedAt":"22/06/2026 00:24:01"}]},{"id":"55136","lat":44.989532,"lon":9.928866,"name":"02698","brand":"Agip Eni","address":"VIA MATTEI 35 29016, CORTEMAGGIORE, PC","prices":[{"type":"petrol","price":1.854,"self":true,"updatedAt":"21/06/2026 01:08:43"},{"type":"diesel","price":1.964,"self":true,"updatedAt":"21/06/2026 01:08:43"}]},{"id":"58947","lat":44.99492064218805,"lon":9.923140327820462,"name":"KEROPETROL CORTEMAGGIORE","brand":"KEROPETROL","address":"Via Giuseppe Galluzzi 27/A  29016, CORTEMAGGIORE, PC","prices":[{"type":"petrol","price":1.879,"self":true,"updatedAt":"17/06/2026 16:41:54"},{"type":"diesel","price":1.979,"self":true,"updatedAt":"17/06/2026 16:41:54"},{"type":"methane","price":1.799,"self":false,"updatedAt":"17/06/2026 16:41:54"},{"type":"lpg","price":0.849,"self":false,"updatedAt":"17/06/2026 16:41:54"}]},{"id":"59606","lat":44.935735257874626,"lon":9.900405307427894,"name":"105601 FIORENZUOLA D'ARDA","brand":"Esso","address":"EMILIA PARMENSE KM 240+900 SNC 29017, FIORENZUOLA D'ARDA, PC","prices":[{"type":"petrol","price":1.779,"self":true,"updatedAt":"22/06/2026 00:45:13"},{"type":"diesel","price":1.879,"self":true,"updatedAt":"22/06/2026 00:45:13"}]},{"id":"50258","lat":44.933208,"lon":9.903579,"name":"2700","brand":"Agip Eni","address":"EUROPA 30 29017, FIORENZUOLA D'ARDA, PC","prices":[{"type":"petrol","price":1.789,"self":true,"updatedAt":"21/06/2026 23:27:21"},{"type":"diesel","price":1.864,"self":true,"updatedAt":"21/06/2026 23:27:21"}]},{"id":"38383","lat":44.932895849307414,"lon":9.903827458620071,"name":"4220","brand":"Tamoil","address":"EUROPA 33 29017, FIORENZUOLA D'ARDA, PC","prices":[{"type":"petrol","price":1.779,"self":true,"updatedAt":"21/06/2026 15:16:07"},{"type":"diesel","price":1.869,"self":true,"updatedAt":"21/06/2026 15:16:07"}]},{"id":"3492","lat":44.9634,"lon":9.90495,"name":"ARDA EST","brand":"Agip Eni","address":"Autostrada A1 MILANO-NAPOLI, Km. 73+300, dir. Nord - -, FIORENZUOLA D'ARDA, PC","prices":[{"type":"petrol","price":1.929,"self":true,"updatedAt":"21/06/2026 15:58:01"},{"type":"diesel","price":2.029,"self":true,"updatedAt":"21/06/2026 15:58:01"},{"type":"lpg","price":0.906,"self":false,"updatedAt":"21/06/2026 15:58:01"}]},{"id":"46660","lat":44.96168407135991,"lon":9.905686811097212,"name":"ARDA OVEST","brand":"Api-Ip","address":"A1 MILANO-NAPOLI, Km. 73, sud - 29017, FIORENZUOLA D'ARDA, PC","prices":[{"type":"petrol","price":1.919,"self":true,"updatedAt":"21/06/2026 22:00:08"},{"type":"diesel","price":2.009,"self":true,"updatedAt":"21/06/2026 22:00:08"},{"type":"methane","price":1.589,"self":false,"updatedAt":"21/06/2026 23:35:45"},{"type":"lpg","price":0.899,"self":false,"updatedAt":"21/06/2026 23:35:45"}]},{"id":"19832","lat":44.92274229765387,"lon":9.922285079956055,"name":"CRISTELLA CARBURANTI SNC COIL","brand":"COIL","address":"VIA SCAPUZZI 36 29017, FIORENZUOLA D'ARDA, PC","prices":[{"type":"petrol","price":1.797,"self":true,"updatedAt":"22/06/2026 00:31:20"},{"type":"diesel","price":1.917,"self":true,"updatedAt":"22/06/2026 00:31:20"}]},{"id":"7306","lat":44.93272237495857,"lon":9.890222278434749,"name":"FIORENZUOLA D'ARDA - SS9 EMILIA.","brand":"Q8","address":"SS9 EMILIA OVEST SN 29017, FIORENZUOLA D'ARDA, PC","prices":[{"type":"petrol","price":1.799,"self":true,"updatedAt":"19/06/2026 15:09:31"},{"type":"diesel","price":1.889,"self":true,"updatedAt":"19/06/2026 15:09:31"},{"type":"lpg","price":0.759,"self":false,"updatedAt":"19/06/2026 15:09:31"}]},{"id":"6468","lat":44.93228291655283,"lon":9.905482836106899,"name":"FIORENZUOLA D'ARDA EUROPA 14","brand":"Q8","address":"VIA EUROPA 14 29017, FIORENZUOLA D'ARDA, PC","prices":[{"type":"petrol","price":1.779,"self":true,"updatedAt":"19/06/2026 15:09:30"},{"type":"diesel","price":1.869,"self":true,"updatedAt":"19/06/2026 15:09:30"}]},{"id":"62691","lat":44.92234,"lon":9.906365,"name":"FIORENZUOLA D'ARDA ST PROVINCIALE PER BARDI KM 1+241","brand":"Q8","address":"ST PROVINCIALE PER BARDI KM 1+241, FIORENZUOLA D'ARDA, PC","prices":[{"type":"petrol","price":1.789,"self":true,"updatedAt":"19/06/2026 12:37:24"},{"type":"diesel","price":1.879,"self":true,"updatedAt":"19/06/2026 12:37:24"},{"type":"lpg","price":0.759,"self":false,"updatedAt":"19/06/2026 12:37:24"}]},{"id":"11753","lat":44.93359583191155,"lon":9.891590205032344,"name":"FIORENZUOLA D’ARDA-SS 9 EMILIA","brand":"Q8","address":"SS 9 EMILIA S/N 29010, FIORENZUOLA D'ARDA, PC","prices":[{"type":"petrol","price":1.799,"self":true,"updatedAt":"21/06/2026 06:33:11"},{"type":"diesel","price":1.889,"self":true,"updatedAt":"21/06/2026 06:33:11"},{"type":"methane","price":1.418,"self":false,"updatedAt":"21/06/2026 06:33:11"}]},{"id":"56046","lat":44.941420284259,"lon":9.88991020882792,"name":"SHELL FIORENZUOLA D'ARDA VIA EMILIA (SS9 KM 241+923)","brand":"Shell","address":"EMILIA KM 241+923,5 SN 29017, FIORENZUOLA D'ARDA, PC","prices":[{"type":"petrol","price":1.799,"self":true,"updatedAt":"22/06/2026 07:31:43"},{"type":"diesel","price":1.929,"self":true,"updatedAt":"22/06/2026 07:31:43"},{"type":"lpg","price":0.769,"self":false,"updatedAt":"22/06/2026 07:31:43"}]},{"id":"31591","lat":44.96445253458959,"lon":9.912033677101135,"name":"STAZIONE DI SERVIZIO EGO ZAFFERANI MARIO","brand":"Ego","address":"LOCALITA' BARABASCA SP462 KM 16+464 SNC 29017, FIORENZUOLA D'ARDA, PC","prices":[{"type":"petrol","price":1.827,"self":false,"updatedAt":"19/06/2026 22:01:00"},{"type":"diesel","price":1.927,"self":false,"updatedAt":"19/06/2026 22:01:00"},{"type":"lpg","price":0.769,"self":false,"updatedAt":"19/06/2026 22:01:00"}]},{"id":"18026","lat":44.92032651027707,"lon":9.925493001937866,"name":"STAZIONE SERVIZIO ENI F.LLI MATERA","brand":"Agip Eni","address":"VIA EMILIA PARMENSE KM 238  29017, FIORENZUOLA D'ARDA, PC","prices":[{"type":"petrol","price":1.825,"self":true,"updatedAt":"20/06/2026 16:46:37"},{"type":"diesel","price":1.914,"self":true,"updatedAt":"20/06/2026 16:46:37"},{"type":"lpg","price":0.702,"self":false,"updatedAt":"20/06/2026 16:46:37"}]},{"id":"49323","lat":44.92268528416023,"lon":9.889858313491837,"name":"Vega Fiorenzuola Nord","brand":"Vega","address":"Strada Statale, Km. 239+350, Piacenza - 29017, FIORENZUOLA D'ARDA, PC","prices":[{"type":"petrol","price":1.789,"self":true,"updatedAt":"20/06/2026 08:10:55"},{"type":"diesel","price":1.879,"self":true,"updatedAt":"20/06/2026 08:10:55"},{"type":"lpg","price":0.759,"self":false,"updatedAt":"20/06/2026 08:10:55"}]},{"id":"49324","lat":44.915991101374544,"lon":9.919305504893495,"name":"Vega Fiorenzuola Sud","brand":"Vega","address":"Strada Statale, Km. 236 ter+300, Parma - 29017, FIORENZUOLA D'ARDA, PC","prices":[{"type":"petrol","price":1.789,"self":true,"updatedAt":"20/06/2026 08:10:58"},{"type":"diesel","price":1.879,"self":true,"updatedAt":"20/06/2026 08:10:58"},{"type":"lpg","price":0.759,"self":false,"updatedAt":"20/06/2026 08:10:58"}]},{"id":"49139","lat":44.9295802487994,"lon":9.900603324536878,"name":"X3CNG ITALIA SRL - FIORENZUOLA","brand":"Pompe Bianche","address":"Via San Protaso Snc 29017, FIORENZUOLA D'ARDA, PC","prices":[{"type":"petrol","price":1.879,"self":true,"updatedAt":"21/06/2026 22:00:26"},{"type":"diesel","price":1.979,"self":true,"updatedAt":"21/06/2026 22:00:26"},{"type":"methane","price":1.589,"self":false,"updatedAt":"21/06/2026 22:00:26"},{"type":"lpg","price":0.789,"self":false,"updatedAt":"21/06/2026 22:00:26"}]},{"id":"49588","lat":44.832598316021674,"lon":9.839866568002504,"name":"NAZZANI","brand":"Pompe Bianche","address":"LOCALITA' RONZONE S.P. 4 29018, LUGAGNANO VAL D'ARDA, PC","prices":[{"type":"petrol","price":1.838,"self":true,"updatedAt":"22/06/2026 00:31:53"},{"type":"diesel","price":1.938,"self":true,"updatedAt":"22/06/2026 00:31:53"},{"type":"lpg","price":0.798,"self":false,"updatedAt":"22/06/2026 00:31:53"}]},{"id":"59167","lat":44.99195834539362,"lon":9.801480016622387,"name":"COIL PONTENURE","brand":"COIL","address":"Via Emilia Est 36  29010, PONTENURE, PC","prices":[{"type":"petrol","price":1.785,"self":true,"updatedAt":"21/06/2026 23:25:58"},{"type":"diesel","price":1.915,"self":true,"updatedAt":"21/06/2026 23:25:58"},{"type":"methane","price":1.497,"self":false,"updatedAt":"21/06/2026 00:47:38"},{"type":"lpg","price":0.765,"self":false,"updatedAt":"21/06/2026 00:47:38"}]},{"id":"53980","lat":44.9997825,"lon":9.7880361,"name":"Q8","brand":"Q8","address":"SS9 km 253+250 29010, PONTENURE, PC","prices":[{"type":"petrol","price":1.779,"self":true,"updatedAt":"22/06/2026 00:25:16"},{"type":"diesel","price":1.889,"self":true,"updatedAt":"22/06/2026 00:25:16"},{"type":"lpg","price":0.779,"self":false,"updatedAt":"22/06/2026 00:25:16"}]},{"id":"54049","lat":44.821854462322364,"lon":9.988756677271775,"name":"106825 - Salsomaggiore - EGI-2GO","brand":"Esso","address":"MATTEOTTI 38 43039, SALSOMAGGIORE TERME, PR","prices":[{"type":"petrol","price":1.799,"self":true,"updatedAt":"20/06/2026 15:06:28"},{"type":"diesel","price":1.899,"self":true,"updatedAt":"20/06/2026 15:06:28"}]},{"id":"57241","lat":44.8125616,"lon":9.98442309,"name":"6935","brand":"Tamoil","address":"Via Magnaghi 1  43039, SALSOMAGGIORE TERME, PR","prices":[{"type":"petrol","price":1.819,"self":true,"updatedAt":"21/06/2026 12:30:28"},{"type":"diesel","price":1.869,"self":true,"updatedAt":"21/06/2026 12:30:28"}]},{"id":"59618","lat":44.815641931138806,"lon":9.987643373724374,"name":"Salsomaggiore","brand":"Pompe Bianche","address":"Via Del Lavoro 14 43039, SALSOMAGGIORE TERME, PR","prices":[{"type":"petrol","price":1.799,"self":true,"updatedAt":"21/06/2026 23:53:01"},{"type":"diesel","price":1.938,"self":true,"updatedAt":"21/06/2026 23:53:01"},{"type":"methane","price":1.499,"self":false,"updatedAt":"21/06/2026 23:53:01"},{"type":"lpg","price":0.799,"self":false,"updatedAt":"21/06/2026 23:53:01"}]},{"id":"53748","lat":44.8167936,"lon":9.9745792,"name":"Stazione di servizio Eni","brand":"Agip Eni","address":"MATTEOTTI 26 43039, SALSOMAGGIORE TERME, PR","prices":[{"type":"petrol","price":1.824,"self":true,"updatedAt":"22/06/2026 07:20:38"},{"type":"diesel","price":1.914,"self":true,"updatedAt":"22/06/2026 07:20:38"}]}]