[{"id":"39865","lat":46.5063310503789,"lon":13.432642221450806,"name":"Bruna Sabotha","brand":"Agip Eni","address":"13 Pontebbana, Km. 80, UDINE - 33010, MALBORGHETTO VALBRUNA, UD","prices":[{"type":"petrol","price":1.989,"self":true,"updatedAt":"22/06/2026 23:45:13"},{"type":"diesel","price":2.029,"self":true,"updatedAt":"22/06/2026 23:45:13"}]},{"id":"54501","lat":46.500773,"lon":13.302107,"name":"Api-Ip","brand":"Api-Ip","address":"VIA CAMILLO BENSO CONTE DI CAVOUR 34, 33016 - -, PONTEBBA, UD","prices":[{"type":"petrol","price":1.929,"self":true,"updatedAt":"29/06/2026 08:32:17"},{"type":"diesel","price":1.959,"self":true,"updatedAt":"29/06/2026 08:32:17"}]},{"id":"54659","lat":46.51008412682895,"lon":13.341705381160232,"name":"AUTOPORTO PONTEBBA","brand":"Pompe Bianche","address":"ZONA  AUTOPORTO SNC 33016, PONTEBBA, UD","prices":[{"type":"petrol","price":1.979,"self":true,"updatedAt":"29/06/2026 18:40:58"},{"type":"diesel","price":2.028,"self":true,"updatedAt":"29/06/2026 18:40:58"}]}]