[{"id":"61442","lat":43.745184051179244,"lon":10.633804150973525,"name":"ALA BIENTINA","brand":"Ala","address":"Via A. Manetti 8/10  56031, BIENTINA, PI","prices":[{"type":"petrol","price":1.779,"self":true,"updatedAt":"01/07/2026 07:28:12"},{"type":"diesel","price":1.849,"self":true,"updatedAt":"01/07/2026 07:28:12"},{"type":"lpg","price":0.729,"self":false,"updatedAt":"01/07/2026 07:34:09"}]},{"id":"6561","lat":43.70758417731088,"lon":10.61864136931149,"name":"BIENTINA MARCO POLO 16","brand":"Q8","address":"VIA MARCO POLO 16 56031, BIENTINA, PI","prices":[{"type":"petrol","price":1.799,"self":true,"updatedAt":"01/07/2026 01:41:37"},{"type":"diesel","price":1.859,"self":true,"updatedAt":"01/07/2026 01:41:37"}]},{"id":"12004","lat":43.72338883156677,"lon":10.513803362846375,"name":"Donati & Giari","brand":"Agip Eni","address":"VIA PROV.LE ARNACCIO-MONTE SERRA SNC 56011, CALCI, PI","prices":[{"type":"petrol","price":1.819,"self":true,"updatedAt":"01/07/2026 00:14:37"},{"type":"diesel","price":1.894,"self":true,"updatedAt":"01/07/2026 00:14:37"}]},{"id":"54604","lat":43.723923,"lon":10.5006258,"name":"Leo e Massi Auto Srl","brand":"Api-Ip","address":"PROVINCIALE LUNGOMONTE 39 56011, CALCI, PI","prices":[{"type":"petrol","price":1.769,"self":true,"updatedAt":"29/06/2026 06:40:51"},{"type":"diesel","price":1.899,"self":true,"updatedAt":"29/06/2026 06:40:51"}]},{"id":"46262","lat":43.68010028100335,"lon":10.584100509855489,"name":"Beyfin","brand":"Beyfin","address":"VIA DELLA BOTTE 66 56012, CALCINAIA, PI","prices":[{"type":"petrol","price":1.789,"self":false,"updatedAt":"30/06/2026 06:53:34"},{"type":"diesel","price":1.859,"self":false,"updatedAt":"30/06/2026 06:53:34"}]},{"id":"5961","lat":43.67455857980305,"lon":10.580048457672092,"name":"CALCINAIA","brand":"Api-Ip","address":"Via Circonvallazione 21 56012, CALCINAIA, PI","prices":[{"type":"petrol","price":1.779,"self":true,"updatedAt":"30/06/2026 13:12:08"},{"type":"diesel","price":1.834,"self":true,"updatedAt":"30/06/2026 13:12:08"}]},{"id":"44719","lat":43.70001075988008,"lon":10.62046080827713,"name":"DISTRIBUTORE ALA CALCINAIA","brand":"Ala","address":"DEL TIGLIO 149 56012, CALCINAIA, PI","prices":[{"type":"petrol","price":1.798,"self":true,"updatedAt":"01/07/2026 00:32:27"},{"type":"diesel","price":1.854,"self":true,"updatedAt":"01/07/2026 00:32:27"}]},{"id":"36559","lat":43.66973299743817,"lon":10.589320957660675,"name":"ENI fornacette 53735","brand":"Agip Eni","address":"via tosco romagnola  km 16+650  56012, CALCINAIA, PI","prices":[{"type":"petrol","price":1.789,"self":true,"updatedAt":"30/06/2026 23:25:54"},{"type":"diesel","price":1.834,"self":true,"updatedAt":"30/06/2026 23:25:54"}]},{"id":"49321","lat":43.68602010959109,"lon":10.606617927551264,"name":"PV CALCINAIA S.P. 2 VICARESE","brand":"Esso","address":"VIA S.P. VICARESE N. 2 - KM 1+550 SNC 56012, CALCINAIA (PI) SNC 56012, CALCINAIA, PI","prices":[{"type":"petrol","price":1.777,"self":true,"updatedAt":"01/07/2026 00:23:11"},{"type":"diesel","price":1.877,"self":true,"updatedAt":"01/07/2026 00:23:11"}]},{"id":"43415","lat":43.58798324635699,"lon":10.673069655895233,"name":"Ciesseci Snc di Casalini Stefano e C.","brand":"Api-Ip","address":"VIA VOLTERRANA 200 56033, CAPANNOLI, PI","prices":[{"type":"petrol","price":1.808,"self":true,"updatedAt":"29/06/2026 06:44:50"},{"type":"diesel","price":1.928,"self":true,"updatedAt":"29/06/2026 06:44:50"}]},{"id":"24186","lat":43.535743713378906,"lon":10.619789123535156,"name":"CASCIANA TERME","brand":"TIBER","address":"VIA DEL COMMERCIO NORD 70 56035, CASCIANA TERME LARI, PI","prices":[{"type":"petrol","price":1.769,"self":true,"updatedAt":"01/07/2026 07:58:10"},{"type":"diesel","price":1.889,"self":true,"updatedAt":"01/07/2026 07:58:10"}]},{"id":"6557","lat":43.52447958466973,"lon":10.620603561401367,"name":"CASCIANA TERME V.DANTE ALIGHIERI 29","brand":"Q8","address":"V.DANTE ALIGHIERI 29 56034, CASCIANA TERME LARI, PI","prices":[{"type":"petrol","price":1.769,"self":true,"updatedAt":"30/06/2026 01:13:03"},{"type":"diesel","price":1.889,"self":true,"updatedAt":"30/06/2026 01:13:03"}]},{"id":"52603","lat":43.60342968086247,"lon":10.570393862460508,"name":"Ciesseci Snc di Casalini Stefano e C.","brand":"Api-Ip","address":"LIVORNESE OVEST 81 56035, CASCIANA TERME LARI, PI","prices":[{"type":"petrol","price":1.808,"self":true,"updatedAt":"29/06/2026 06:44:58"},{"type":"diesel","price":1.928,"self":true,"updatedAt":"29/06/2026 06:44:58"}]},{"id":"9233","lat":43.5821636347685,"lon":10.629213452339172,"name":"GIRASOLE S.R.L. CONAD","brand":"CONAD","address":"VIA DEL COMMERCIO 48 56035, CASCIANA TERME LARI, PI","prices":[{"type":"petrol","price":1.739,"self":true,"updatedAt":"01/07/2026 07:14:55"},{"type":"diesel","price":1.829,"self":true,"updatedAt":"01/07/2026 07:14:55"}]},{"id":"11764","lat":43.581468660329605,"lon":10.629673177909808,"name":"LARI-FZ.CEVOLI VIA DEL COMMERCIO 95","brand":"Q8","address":"FZ.CEVOLI VIA DEL COMMERCIO 95 56030, CASCIANA TERME LARI, PI","prices":[{"type":"petrol","price":1.779,"self":true,"updatedAt":"01/07/2026 07:43:50"},{"type":"diesel","price":1.899,"self":true,"updatedAt":"01/07/2026 07:43:50"}]},{"id":"12484","lat":43.57037067989727,"lon":10.594018176198006,"name":"QUATTROPETROLI","brand":"Quattro Petroli","address":"VIA XVI LUGLIO , LARI (PI) 2 56035, CASCIANA TERME LARI, PI","prices":[{"type":"petrol","price":1.759,"self":true,"updatedAt":"30/06/2026 11:19:39"},{"type":"diesel","price":1.869,"self":true,"updatedAt":"30/06/2026 11:19:38"}]},{"id":"51011","lat":43.683295038710696,"lon":10.510976932173623,"name":"53750 – Cascina","brand":"Agip Eni","address":"Loc. San Frediano - CASCINA  56021, CASCINA, PI","prices":[{"type":"petrol","price":1.819,"self":true,"updatedAt":"01/07/2026 00:43:55"},{"type":"diesel","price":1.894,"self":true,"updatedAt":"01/07/2026 00:43:55"}]},{"id":"61300","lat":43.66250908174845,"lon":10.542115053590413,"name":"ALA LATIGNANO","brand":"Ala","address":"VIA NAZARIO SAURO SNC - LOC. LATIGNANO  56021, CASCINA, PI","prices":[{"type":"petrol","price":1.767,"self":true,"updatedAt":"30/06/2026 23:44:13"},{"type":"diesel","price":1.877,"self":true,"updatedAt":"30/06/2026 23:44:13"}]},{"id":"42566","lat":43.66758404476622,"lon":10.55734509286799,"name":"Beyfin","brand":"Beyfin","address":"S.S. 67 bis Arnaccio 16/a 56021, CASCINA, PI","prices":[{"type":"petrol","price":1.789,"self":true,"updatedAt":"29/06/2026 09:39:12"},{"type":"diesel","price":1.859,"self":true,"updatedAt":"29/06/2026 09:39:12"},{"type":"lpg","price":0.749,"self":false,"updatedAt":"29/06/2026 09:39:12"}]},{"id":"8614","lat":43.668145096730186,"lon":10.524512409787008,"name":"CASCINA LOC.MARCIANA SUPERSTR.FI/PI/LI","brand":"Q8","address":"LOC.MARCIANA SUPERSTR.FI/PI/LI  56021, CASCINA, PI","prices":[{"type":"petrol","price":1.769,"self":true,"updatedAt":"30/06/2026 07:44:39"},{"type":"diesel","price":1.849,"self":true,"updatedAt":"30/06/2026 07:44:39"},{"type":"lpg","price":0.739,"self":false,"updatedAt":"30/06/2026 07:44:39"}]},{"id":"30850","lat":43.6340712867068,"lon":10.58691142573241,"name":"Cascina Sud","brand":"Api-Ip","address":"GRANDE COMUNICAZIONE S.N.C. 56021, CASCINA, PI","prices":[{"type":"petrol","price":1.788,"self":true,"updatedAt":"25/06/2026 15:14:46"},{"type":"diesel","price":1.908,"self":true,"updatedAt":"25/06/2026 15:14:46"},{"type":"lpg","price":0.708,"self":false,"updatedAt":"25/06/2026 15:14:46"}]},{"id":"11762","lat":43.681302145456094,"lon":10.522267406082165,"name":"CASCINA-LOC.SAN FREDIANO A SETTIMO V. TOSCO","brand":"Q8","address":"LOC.SAN FREDIANO A SETTIMO V. TOSCO S/N 56026, CASCINA, PI","prices":[{"type":"petrol","price":1.799,"self":true,"updatedAt":"01/07/2026 01:41:34"},{"type":"diesel","price":1.829,"self":true,"updatedAt":"01/07/2026 01:41:34"}]},{"id":"30604","lat":43.66333797029339,"lon":10.540913880442758,"name":"NEW GAS NETWORK","brand":"Pompe Bianche","address":"RIO POZZALE SN 56021, CASCINA, PI","prices":[{"type":"petrol","price":1.769,"self":true,"updatedAt":"30/06/2026 17:47:03"},{"type":"diesel","price":1.839,"self":true,"updatedAt":"30/06/2026 12:36:55"},{"type":"methane","price":1.769,"self":false,"updatedAt":"30/06/2026 11:46:48"},{"type":"lpg","price":0.729,"self":false,"updatedAt":"30/06/2026 19:26:39"}]},{"id":"41909","lat":43.66907218630058,"lon":10.541029125452042,"name":"PISA CARBURANTI CASCINA","brand":"Pompe Bianche","address":"VIA NAZARIO SAURO 124 56021, CASCINA, PI","prices":[{"type":"petrol","price":1.779,"self":true,"updatedAt":"29/06/2026 09:58:18"},{"type":"diesel","price":1.849,"self":true,"updatedAt":"29/06/2026 09:58:18"},{"type":"methane","price":1.769,"self":false,"updatedAt":"29/06/2026 09:58:18"},{"type":"lpg","price":0.739,"self":false,"updatedAt":"29/06/2026 09:58:18"}]},{"id":"50201","lat":43.678233420148416,"lon":10.537764925746648,"name":"STAZIONE DI SERVIZIO ENI","brand":"Agip Eni","address":"VIA TOSCOROMAGNOLA 626 56021, CASCINA, PI","prices":[{"type":"petrol","price":1.814,"self":true,"updatedAt":"30/06/2026 00:08:06"},{"type":"diesel","price":1.889,"self":true,"updatedAt":"30/06/2026 06:20:08"}]},{"id":"24601","lat":43.72175668312704,"lon":10.745546221733093,"name":"CASTELFRANCO DI SOTTO","brand":"Agip Eni","address":"VIA FRANCESCA BIS  56022, CASTELFRANCO DI SOTTO, PI","prices":[{"type":"petrol","price":1.814,"self":true,"updatedAt":"30/06/2026 09:26:57"},{"type":"diesel","price":1.884,"self":true,"updatedAt":"30/06/2026 10:45:37"},{"type":"methane","price":1.699,"self":false,"updatedAt":"27/06/2026 07:03:20"},{"type":"lpg","price":0.762,"self":false,"updatedAt":"27/06/2026 07:04:24"}]},{"id":"62131","lat":43.69780310847159,"lon":10.726614747997232,"name":"Eni","brand":"Agip Eni","address":"PROV.LE FRANCESCA SUD 197 56022, CASTELFRANCO DI SOTTO, PI","prices":[{"type":"petrol","price":1.829,"self":true,"updatedAt":"30/06/2026 00:09:44"},{"type":"diesel","price":1.894,"self":true,"updatedAt":"30/06/2026 00:09:44"}]},{"id":"7074","lat":43.69901205071147,"lon":10.739494646388266,"name":"FABBRI E ZUCCHELLI","brand":"Api-Ip","address":"VIA PROVINCIALE FRANCESCA SUD 66 56022, CASTELFRANCO DI SOTTO, PI","prices":[{"type":"petrol","price":1.959,"self":true,"updatedAt":"03/06/2026 08:12:16"},{"type":"diesel","price":2.019,"self":true,"updatedAt":"03/06/2026 08:12:16"}]},{"id":"63264","lat":43.699020190656384,"lon":10.739480968717183,"name":"IP 46763","brand":"Api-Ip","address":"Via Francesca Sud 66  56022, CASTELFRANCO DI SOTTO, PI","prices":[{"type":"petrol","price":1.829,"self":true,"updatedAt":"30/06/2026 08:39:55"},{"type":"diesel","price":1.924,"self":true,"updatedAt":"30/06/2026 08:39:55"}]},{"id":"21596","lat":43.60948756716238,"lon":10.527127042991651,"name":"IP","brand":"Api-Ip","address":"LAVORIA 1 INT.B 56042, CRESPINA LORENZANA, PI","prices":[{"type":"petrol","price":1.778,"self":true,"updatedAt":"26/06/2026 15:22:29"},{"type":"diesel","price":1.898,"self":true,"updatedAt":"26/06/2026 15:22:29"}]},{"id":"55188","lat":43.60666,"lon":10.53455,"name":"VIA VENETO SNC CRESPINA LORENZANA (PI) CAP 56042","brand":"Api-Ip","address":"VENETO  SNC 56042, CRESPINA LORENZANA, PI","prices":[{"type":"petrol","price":1.777,"self":true,"updatedAt":"30/06/2026 17:18:56"},{"type":"diesel","price":1.897,"self":true,"updatedAt":"30/06/2026 17:18:56"}]},{"id":"20110","lat":43.551613971970845,"lon":10.505634930059387,"name":"Fauglia","brand":"Api-Ip","address":"Via Marconi, Acciaiolo   56043, FAUGLIA, PI","prices":[{"type":"petrol","price":1.774,"self":true,"updatedAt":"30/06/2026 09:14:54"},{"type":"diesel","price":1.884,"self":true,"updatedAt":"30/06/2026 09:14:54"}]},{"id":"33024","lat":43.59241942625319,"lon":10.718965131282857,"name":"PALAIA - MONTANELLI","brand":"Api-Ip","address":"VIA PROVINCIALE PER LEGOLI  56030, PALAIA, PI","prices":[{"type":"petrol","price":1.799,"self":true,"updatedAt":"30/06/2026 13:04:23"},{"type":"diesel","price":1.899,"self":true,"updatedAt":"30/06/2026 13:04:23"}]},{"id":"46164","lat":43.5654914294841,"lon":10.71079761021582,"name":"beyfin","brand":"Beyfin","address":"STRADA PROV.LE DELLA FILA 36 56037, PECCIOLI, PI","prices":[{"type":"petrol","price":1.799,"self":true,"updatedAt":"29/06/2026 06:51:51"},{"type":"diesel","price":1.909,"self":true,"updatedAt":"29/06/2026 06:51:51"},{"type":"lpg","price":0.759,"self":false,"updatedAt":"29/06/2026 06:51:51"}]},{"id":"60585","lat":43.58522992901685,"lon":10.676285832934557,"name":"Aquila Drive - Capannoli","brand":"Aquila","address":"Via Volterrana 314  56033, PISA, PI","prices":[{"type":"petrol","price":1.789,"self":true,"updatedAt":"30/06/2026 23:29:39"},{"type":"diesel","price":1.869,"self":true,"updatedAt":"30/06/2026 23:29:39"}]},{"id":"60638","lat":43.622003,"lon":10.605731,"name":"Aquila Drive - Ponsacco","brand":"Aquila","address":"Via Fossa nuova SRT439 - sp 67, PONSACCO, PI","prices":[{"type":"petrol","price":1.759,"self":true,"updatedAt":"30/06/2026 23:29:28"},{"type":"diesel","price":1.859,"self":true,"updatedAt":"30/06/2026 23:29:28"},{"type":"lpg","price":0.698,"self":false,"updatedAt":"30/06/2026 23:29:28"}]},{"id":"61370","lat":43.63110543935799,"lon":10.658594369888306,"name":"Aquila Drive - Ponsacco Val di Cava","brand":"Q8","address":"Via delle Colline 1/L 56038, PONSACCO, PI","prices":[{"type":"petrol","price":1.799,"self":true,"updatedAt":"30/06/2026 23:51:50"},{"type":"diesel","price":1.899,"self":true,"updatedAt":"30/06/2026 23:51:50"},{"type":"lpg","price":0.699,"self":false,"updatedAt":"30/06/2026 23:51:50"}]},{"id":"51656","lat":43.62869087645959,"lon":10.629396763492528,"name":"ESSO - PONSACCO VIA VALDERA P, 150","brand":"Esso","address":"VIA VALDERA P 150 56038, PONSACCO, PI","prices":[{"type":"petrol","price":1.759,"self":true,"updatedAt":"01/07/2026 07:15:00"},{"type":"diesel","price":1.849,"self":true,"updatedAt":"01/07/2026 07:15:00"}]},{"id":"13839","lat":43.6177393281434,"lon":10.616680160164833,"name":"Kerotris - Ponsacco","brand":"Kerotris","address":"VIA CIRCONVALLAZIONE LOTTO 3 56038, PONSACCO, PI","prices":[{"type":"petrol","price":1.769,"self":true,"updatedAt":"29/06/2026 10:58:26"},{"type":"diesel","price":1.849,"self":true,"updatedAt":"29/06/2026 10:58:26"},{"type":"lpg","price":0.699,"self":false,"updatedAt":"29/06/2026 10:58:26"}]},{"id":"22297","lat":43.62928634268702,"lon":10.603405237197876,"name":"QUATTROPETROLI - PONSACCO","brand":"Quattro Petroli","address":"VIA NUOVA CIRCONVALLAZIONE, S.R. 439 SNC 56038, PONSACCO, PI","prices":[{"type":"petrol","price":1.758,"self":true,"updatedAt":"26/06/2026 09:46:47"},{"type":"diesel","price":1.868,"self":true,"updatedAt":"26/06/2026 09:46:47"},{"type":"lpg","price":0.698,"self":false,"updatedAt":"26/06/2026 09:46:47"}]},{"id":"26827","lat":43.615097829384986,"lon":10.641200244426727,"name":"RIFORNIMENTO GIANNINI","brand":"Api-Ip","address":"VIA VALDERA C 79 56038, PONSACCO, PI","prices":[{"type":"petrol","price":1.778,"self":true,"updatedAt":"30/06/2026 07:23:39"},{"type":"diesel","price":1.898,"self":true,"updatedAt":"30/06/2026 07:23:39"}]},{"id":"61036","lat":43.66566,"lon":10.63558,"name":"5269 PONTEDERA","brand":"Agip Eni","address":"VIA TOSCO ROMAGMNOLA KM 20+562  SNC 0124, PONTEDERA, PI","prices":[{"type":"petrol","price":1.824,"self":true,"updatedAt":"30/06/2026 23:56:25"},{"type":"diesel","price":1.889,"self":true,"updatedAt":"30/06/2026 23:56:25"}]},{"id":"41594","lat":43.64758818813079,"lon":10.606263875961304,"name":"ADS PONTEDERA","brand":"Ala","address":"VIALE EUROPA SNC 56025, PONTEDERA (PI) SNC 56025, PONTEDERA, PI","prices":[{"type":"petrol","price":1.799,"self":true,"updatedAt":"01/07/2026 07:16:02"},{"type":"diesel","price":1.899,"self":true,"updatedAt":"01/07/2026 00:30:41"},{"type":"methane","price":1.499,"self":false,"updatedAt":"01/07/2026 00:30:41"},{"type":"lpg","price":0.697,"self":false,"updatedAt":"01/07/2026 00:30:41"}]},{"id":"60851","lat":43.65211,"lon":10.6124,"name":"ADS STRADA DI PATTO","brand":"Q8","address":"SS439 VAR.PONTEDERA PONSACCO - STRADA DI PATTO  56025, PONTEDERA, PI","prices":[{"type":"petrol","price":1.799,"self":true,"updatedAt":"30/06/2026 00:19:16"},{"type":"diesel","price":1.899,"self":true,"updatedAt":"30/06/2026 00:19:16"},{"type":"methane","price":1.699,"self":false,"updatedAt":"30/06/2026 23:17:06"},{"type":"lpg","price":0.699,"self":false,"updatedAt":"30/06/2026 23:17:06"}]},{"id":"62037","lat":43.61951844205676,"lon":10.67325803991701,"name":"ALA I FABBRI","brand":"Ala","address":"VIA PROVINCIALE COLLINE - LOC. I FABBRI  56026, PONTEDERA, PI","prices":[{"type":"petrol","price":1.789,"self":true,"updatedAt":"01/07/2026 00:02:12"},{"type":"diesel","price":1.869,"self":true,"updatedAt":"01/07/2026 00:02:12"},{"type":"lpg","price":0.699,"self":false,"updatedAt":"01/07/2026 00:02:12"}]},{"id":"59216","lat":43.641248575517665,"lon":10.595445550154116,"name":"B-PETROL PONTEDERA (PI)","brand":"bpetrol","address":"Via di Gello Est 1 56025, PONTEDERA, PI","prices":[{"type":"petrol","price":1.758,"self":true,"updatedAt":"30/06/2026 23:22:42"},{"type":"lpg","price":0.698,"self":false,"updatedAt":"30/06/2026 23:22:42"}]},{"id":"54086","lat":43.66751461449978,"lon":10.605561733245809,"name":"BEYFIN PONTEDERA","brand":"Beyfin","address":"TOSCO ROMAGNOLA 18+018 SNC 56025, PONTEDERA, PI","prices":[{"type":"petrol","price":1.799,"self":true,"updatedAt":"29/06/2026 08:40:23"},{"type":"diesel","price":1.879,"self":true,"updatedAt":"29/06/2026 08:40:23"},{"type":"lpg","price":0.749,"self":false,"updatedAt":"29/06/2026 08:40:23"}]},{"id":"43993","lat":43.63458428413617,"lon":10.588889122009277,"name":"ENI PONTEDERA NORD","brand":"Agip Eni","address":"SGC FI-PI-LI KM. 56,875 56025, PONTEDERA, PI","prices":[{"type":"petrol","price":1.799,"self":true,"updatedAt":"01/07/2026 00:02:58"},{"type":"diesel","price":1.859,"self":true,"updatedAt":"01/07/2026 00:27:54"},{"type":"methane","price":1.397,"self":false,"updatedAt":"01/07/2026 00:02:58"}]},{"id":"57384","lat":43.653445,"lon":10.64996,"name":"ESSO PONTEDERA VIALE EUROPA","brand":"Esso","address":"EUROPA SNC 56025, PONTEDERA, PI","prices":[{"type":"petrol","price":1.789,"self":true,"updatedAt":"01/07/2026 07:23:55"},{"type":"diesel","price":1.889,"self":true,"updatedAt":"01/07/2026 07:23:55"}]},{"id":"49273","lat":43.664371865643155,"lon":10.70022413988113,"name":"EUROPAM - PONTEDERA","brand":"Europam","address":"S.S.67 KM.26 + 210 snc 56025, PONTEDERA, PI","prices":[{"type":"petrol","price":1.777,"self":true,"updatedAt":"29/06/2026 11:23:26"},{"type":"diesel","price":1.857,"self":true,"updatedAt":"29/06/2026 11:23:26"}]},{"id":"33622","lat":43.6566593818604,"lon":10.602123141288757,"name":"GOLDENGAS ENI/ PONTEDERA","brand":"Agip Eni","address":"VIALE AMERICA 15 56025, PONTEDERA, PI","prices":[{"type":"petrol","price":1.819,"self":true,"updatedAt":"30/06/2026 09:01:37"},{"type":"diesel","price":1.889,"self":true,"updatedAt":"30/06/2026 09:01:37"},{"type":"lpg","price":0.699,"self":false,"updatedAt":"30/06/2026 09:01:37"}]},{"id":"57974","lat":43.64164224705071,"lon":10.650618248171767,"name":"GOLDENGAS SHELL PONTEDERA","brand":"Shell","address":"S.P. 11 KM 2+808 SNC 56025, PONTEDERA, PI","prices":[{"type":"petrol","price":1.779,"self":true,"updatedAt":"30/06/2026 09:02:00"},{"type":"diesel","price":1.879,"self":true,"updatedAt":"30/06/2026 09:02:00"},{"type":"methane","price":1.399,"self":false,"updatedAt":"30/06/2026 09:02:00"},{"type":"lpg","price":0.699,"self":false,"updatedAt":"30/06/2026 09:02:00"}]},{"id":"55254","lat":43.666541848054194,"lon":10.649274944725047,"name":"IP 45951","brand":"Api-Ip","address":"SS 67 TOSCO ROMAGNOLA KM21+696 56025, PONTEDERA, PI","prices":[{"type":"petrol","price":1.799,"self":true,"updatedAt":"26/06/2026 17:14:02"},{"type":"diesel","price":1.899,"self":true,"updatedAt":"26/06/2026 17:14:02"}]},{"id":"61194","lat":43.65479720107459,"lon":10.631187558174133,"name":"IP 47634","brand":"Api-Ip","address":"Via Roma 326 56025, PONTEDERA, PI","prices":[{"type":"petrol","price":1.786,"self":true,"updatedAt":"26/06/2026 17:14:12"},{"type":"diesel","price":1.889,"self":true,"updatedAt":"26/06/2026 17:14:12"}]},{"id":"62910","lat":43.64066350496414,"lon":10.617187867431621,"name":"IP FM PETROL VALDERA","brand":"Api-Ip","address":"SGC FI-PI-LI  56025, PONTEDERA, PI","prices":[{"type":"petrol","price":1.796,"self":true,"updatedAt":"30/06/2026 12:58:59"},{"type":"diesel","price":1.866,"self":true,"updatedAt":"30/06/2026 12:58:59"},{"type":"methane","price":1.499,"self":true,"updatedAt":"30/06/2026 12:58:59"},{"type":"lpg","price":0.727,"self":true,"updatedAt":"30/06/2026 12:58:59"}]},{"id":"54244","lat":43.64168352565656,"lon":10.617576122283928,"name":"IP45603","brand":"Api-Ip","address":"S.G.C. FI.PI.LI. DIR. FIRENZE KM54+140 56025, PONTEDERA, PI","prices":[{"type":"petrol","price":1.789,"self":true,"updatedAt":"29/06/2026 12:51:05"},{"type":"diesel","price":1.859,"self":true,"updatedAt":"29/06/2026 12:51:05"},{"type":"methane","price":1.429,"self":false,"updatedAt":"29/06/2026 12:51:05"},{"type":"lpg","price":0.729,"self":false,"updatedAt":"29/06/2026 12:51:05"}]},{"id":"47422","lat":43.645807621101994,"lon":10.62676727771759,"name":"Pisa - Pontedera La Borra","brand":"Beyfin","address":"VIA DELLA FORNACE SNC 56025, PONTEDERA, PI","prices":[{"type":"petrol","price":1.759,"self":true,"updatedAt":"01/07/2026 00:14:17"},{"type":"diesel","price":1.879,"self":true,"updatedAt":"01/07/2026 00:14:17"},{"type":"methane","price":1.499,"self":false,"updatedAt":"01/07/2026 00:14:17"},{"type":"lpg","price":0.699,"self":false,"updatedAt":"01/07/2026 00:14:17"}]},{"id":"28314","lat":43.655831049239325,"lon":10.632016851520575,"name":"PONTEDERA - ROMA","brand":"Api-Ip","address":"VIA ROMA  56025, PONTEDERA, PI","prices":[{"type":"petrol","price":1.779,"self":true,"updatedAt":"30/06/2026 19:02:22"},{"type":"diesel","price":1.879,"self":true,"updatedAt":"30/06/2026 19:02:22"}]},{"id":"31171","lat":43.63356212151889,"lon":10.6032839067459,"name":"PONTEDERA - SP DI GELLO 35/A","brand":"Api-Ip","address":"SP DI GELLO 35/A 56030, PONTEDERA, PI","prices":[{"type":"petrol","price":1.849,"self":true,"updatedAt":"30/06/2026 09:02:09"},{"type":"diesel","price":1.959,"self":true,"updatedAt":"30/06/2026 09:02:09"},{"type":"lpg","price":0.788,"self":false,"updatedAt":"30/06/2026 09:02:09"}]},{"id":"43030","lat":43.638181728998646,"lon":10.62877893447876,"name":"PONTEDERA B.FUEL","brand":"Pompe Bianche","address":"via SRT 439 km 61+815  56025, PONTEDERA, PI","prices":[{"type":"petrol","price":1.759,"self":true,"updatedAt":"30/06/2026 15:37:02"},{"type":"diesel","price":1.859,"self":true,"updatedAt":"30/06/2026 15:37:01"},{"type":"methane","price":1.499,"self":false,"updatedAt":"30/06/2026 16:46:45"},{"type":"lpg","price":0.699,"self":false,"updatedAt":"30/06/2026 11:26:43"}]},{"id":"55332","lat":43.6327395,"lon":10.595817,"name":"PONTEDERA S.G.C.FI-PI-LI KM 56+750-GELLO","brand":"Q8","address":"S.G.C.FI-PI-LI KM 56+750-GELLO  56025, PONTEDERA, PI","prices":[{"type":"petrol","price":1.789,"self":true,"updatedAt":"01/07/2026 07:43:49"},{"type":"diesel","price":1.859,"self":true,"updatedAt":"01/07/2026 07:43:49"}]},{"id":"11767","lat":43.666920293670934,"lon":10.64759807605742,"name":"PONTEDERA-VIA TOSCO ROMAGNOLA 237","brand":"Q8","address":"VIA TOSCO ROMAGNOLA 237 56025, PONTEDERA, PI","prices":[{"type":"petrol","price":1.789,"self":true,"updatedAt":"01/07/2026 07:43:50"},{"type":"diesel","price":1.879,"self":true,"updatedAt":"01/07/2026 07:43:50"}]},{"id":"63037","lat":43.6622107,"lon":10.6416422,"name":"S.P.DELLE COLLINE PER LEGOLI KM 7+100","brand":"Api-Ip","address":"Via delle Colline per Legoli 80  56025, PONTEDERA, PI","prices":[{"type":"petrol","price":1.839,"self":true,"updatedAt":"30/06/2026 17:19:19"},{"type":"diesel","price":1.949,"self":true,"updatedAt":"30/06/2026 17:19:19"},{"type":"methane","price":1.429,"self":true,"updatedAt":"30/06/2026 17:19:19"}]},{"id":"40367","lat":43.64164304131975,"lon":10.650343894958496,"name":"Stazione di Servizio Shell di Casalini Moreno","brand":"Shell","address":"strada provinciale 11 delle colline Legoli  Km 2+808 56025, PONTEDERA, PI","prices":[{"type":"petrol","price":1.779,"self":true,"updatedAt":"01/07/2026 07:45:14"},{"type":"diesel","price":1.879,"self":true,"updatedAt":"01/07/2026 07:45:14"},{"type":"methane","price":1.399,"self":false,"updatedAt":"01/07/2026 07:45:14"},{"type":"lpg","price":0.699,"self":false,"updatedAt":"01/07/2026 07:45:13"}]},{"id":"61917","lat":43.7063202,"lon":10.7482288,"name":"EDRA ENERGIA - SANTA CROCE","brand":"Edra Energia","address":"Via G. di Vittorio  56029, SANTA CROCE SULL'ARNO, PI","prices":[{"type":"petrol","price":1.838,"self":true,"updatedAt":"26/06/2026 14:03:46"},{"type":"diesel","price":1.919,"self":true,"updatedAt":"26/06/2026 14:03:46"}]},{"id":"19201","lat":43.68991857009533,"lon":10.688364878296852,"name":"AREA SERVICE LA STRANIERA DI NANNETTI SILVIA & C. S.A.S.","brand":"Beyfin","address":"VIA FRANCESCA 434 56020, SANTA MARIA A MONTE, PI","prices":[{"type":"petrol","price":1.839,"self":true,"updatedAt":"01/07/2026 06:40:34"},{"type":"diesel","price":1.919,"self":true,"updatedAt":"01/07/2026 06:40:34"},{"type":"lpg","price":0.749,"self":false,"updatedAt":"01/07/2026 06:40:34"}]},{"id":"37775","lat":43.68441602706241,"lon":10.66079244017601,"name":"DECA PETROL MONTECALVOLI","brand":"Pompe Bianche","address":"Via Provinciale Francesca  545 56030, SANTA MARIA A MONTE, PI","prices":[{"type":"petrol","price":1.793,"self":true,"updatedAt":"27/06/2026 07:59:57"},{"type":"diesel","price":1.893,"self":true,"updatedAt":"27/06/2026 07:59:57"}]},{"id":"59921","lat":43.690751,"lon":10.708251,"name":"GOLDENGAS SHELL SANTA MARIA A MONTE","brand":"Shell","address":"STRADA PROVINCIALE FRANCESCA - SP 66 - KM 1+870, SANTA MARIA A MONTE, PI","prices":[{"type":"petrol","price":1.829,"self":true,"updatedAt":"30/06/2026 09:01:43"},{"type":"diesel","price":1.899,"self":true,"updatedAt":"30/06/2026 09:01:43"},{"type":"lpg","price":0.759,"self":false,"updatedAt":"30/06/2026 09:01:43"}]},{"id":"45979","lat":43.69476822527333,"lon":10.705715417861938,"name":"PV 4146","brand":"Q8","address":"S.P. FRANCESCA SUD 160 56020, SANTA MARIA A MONTE, PI","prices":[{"type":"petrol","price":1.824,"self":true,"updatedAt":"27/06/2026 07:15:57"},{"type":"diesel","price":1.894,"self":true,"updatedAt":"27/06/2026 07:15:57"}]},{"id":"6556","lat":43.68558659621149,"lon":10.670400112867355,"name":"SANTA MARIA A MONTE LOC.MONTECALVOLI","brand":"Q8","address":"LOC.MONTECALVOLI SNC 56020, SANTA MARIA A MONTE, PI","prices":[{"type":"petrol","price":1.794,"self":true,"updatedAt":"01/07/2026 01:41:34"},{"type":"diesel","price":1.894,"self":true,"updatedAt":"01/07/2026 01:41:34"}]},{"id":"62020","lat":43.55516758580229,"lon":10.641540165842622,"name":"ALA TERRICCIOLA","brand":"Ala","address":"VIA SOLFERINO - LOC. SOIANELLA 1 56030, TERRICCIOLA, PI","prices":[{"type":"petrol","price":1.599,"self":true,"updatedAt":"01/07/2026 00:01:37"},{"type":"diesel","price":1.619,"self":true,"updatedAt":"01/07/2026 00:01:37"}]},{"id":"63375","lat":43.5676668,"lon":10.6890144,"name":"EUROPAM - TERRICCIOLA","brand":"Europam","address":"Via Volterrana 9  56030, TERRICCIOLA, PI","prices":[{"type":"petrol","price":1.797,"self":true,"updatedAt":"26/06/2026 18:00:05"},{"type":"diesel","price":1.897,"self":true,"updatedAt":"26/06/2026 18:00:05"}]},{"id":"50460","lat":43.542404533471185,"lon":10.704190012740591,"name":"IP STAZ SERV TERRICCIOLA LOC. LA ROSA.","brand":"Api-Ip","address":"VIA SALAIOLA NORD N. 17 - LOC. LA ROSA 17 56030, TERRICCIOLA, PI","prices":[{"type":"petrol","price":1.859,"self":true,"updatedAt":"30/06/2026 17:17:59"},{"type":"diesel","price":1.969,"self":true,"updatedAt":"30/06/2026 17:17:59"}]},{"id":"46678","lat":43.54700656549693,"lon":10.698264880950887,"name":"nessuno","brand":"Aquila","address":"via volterrana 335 56030, TERRICCIOLA, PI","prices":[{"type":"petrol","price":1.789,"self":true,"updatedAt":"29/06/2026 10:03:04"},{"type":"diesel","price":1.879,"self":true,"updatedAt":"29/06/2026 10:03:04"},{"type":"methane","price":1.699,"self":false,"updatedAt":"29/06/2026 10:03:04"},{"type":"lpg","price":0.759,"self":false,"updatedAt":"29/06/2026 10:03:04"}]},{"id":"6888","lat":43.70381407440523,"lon":10.602455735206604,"name":"BEYFIN","brand":"Beyfin","address":"VIA FRANCESCA NORD 29/A 56010, VICOPISANO, PI","prices":[{"type":"petrol","price":1.789,"self":true,"updatedAt":"29/06/2026 17:45:56"},{"type":"diesel","price":1.859,"self":true,"updatedAt":"29/06/2026 17:45:56"},{"type":"methane","price":1.699,"self":false,"updatedAt":"29/06/2026 17:45:56"},{"type":"lpg","price":0.749,"self":false,"updatedAt":"29/06/2026 17:45:56"}]},{"id":"54586","lat":43.68488488155244,"lon":10.54798463906859,"name":"IP 40696","brand":"Api-Ip","address":"PROVINCIALE VICARESE KM 6,280 56010, VICOPISANO, PI","prices":[{"type":"petrol","price":1.776,"self":true,"updatedAt":"26/06/2026 17:13:56"},{"type":"diesel","price":1.899,"self":true,"updatedAt":"26/06/2026 17:13:56"},{"type":"lpg","price":0.729,"self":false,"updatedAt":"26/06/2026 17:13:56"}]},{"id":"34336","lat":43.70227252923545,"lon":10.597033649682999,"name":"San Carlo Vicopisano","brand":"Aquila","address":"Via Francesca Nord 23 56010, VICOPISANO, PI","prices":[{"type":"petrol","price":1.799,"self":true,"updatedAt":"27/06/2026 08:22:46"},{"type":"diesel","price":1.889,"self":true,"updatedAt":"27/06/2026 08:22:46"},{"type":"lpg","price":0.739,"self":false,"updatedAt":"27/06/2026 08:22:46"}]},{"id":"11766","lat":43.719927344272186,"lon":10.617494881153107,"name":"VICOPISANO-VIA SARZANESE 28 - LOC. RISAIE","brand":"Q8","address":"VIA SARZANESE - LOC. RISAIE 28 56010, VICOPISANO, PI","prices":[{"type":"petrol","price":1.839,"self":true,"updatedAt":"01/07/2026 07:43:52"},{"type":"diesel","price":1.899,"self":true,"updatedAt":"01/07/2026 07:43:52"}]}]