[{"id":"43394","lat":43.510756653063474,"lon":11.8712063412376,"name":"ESSO AREZZO - SITORNI","brand":"Esso","address":"Via Umbro Casentinese - Fraz. Giovi - Loc. Sitorni  52100, AREZZO, AR","prices":[{"type":"petrol","price":1.779,"self":true,"updatedAt":"28/06/2026 07:21:13"},{"type":"diesel","price":1.859,"self":true,"updatedAt":"28/06/2026 07:21:13"}]},{"id":"40312","lat":43.5082160028992,"lon":11.785018891096115,"name":"EUROPAM - AREZZO","brand":"Europam","address":"LOCALITA' DOCCIA RONDINE  52100, AREZZO, AR","prices":[{"type":"petrol","price":1.767,"self":true,"updatedAt":"26/06/2026 13:37:45"},{"type":"diesel","price":1.827,"self":true,"updatedAt":"26/06/2026 13:37:45"}]},{"id":"4214","lat":43.69424176833497,"lon":11.802805598384566,"name":"AREA DI SERVIZIO LECHIANE","brand":"Piccini Energy","address":"VIA BUONCONTE DA MONTEFELTRO 9 52011, BIBBIENA, AR","prices":[{"type":"petrol","price":1.809,"self":true,"updatedAt":"25/06/2026 12:34:36"},{"type":"diesel","price":1.889,"self":true,"updatedAt":"25/06/2026 12:34:36"},{"type":"methane","price":1.499,"self":false,"updatedAt":"25/06/2026 12:34:36"},{"type":"lpg","price":0.799,"self":false,"updatedAt":"25/06/2026 12:34:36"}]},{"id":"48970","lat":43.70187725169301,"lon":11.804056880538951,"name":"BIBBIENA CARBURANTI","brand":"Bibbiena Carburanti","address":"VIA LOC. PALAZZETTO 0 52011, BIBBIENA (AR) SNC 52011, BIBBIENA, AR","prices":[{"type":"petrol","price":1.809,"self":true,"updatedAt":"26/06/2026 12:02:23"},{"type":"diesel","price":1.879,"self":true,"updatedAt":"26/06/2026 12:02:23"},{"type":"lpg","price":0.799,"self":false,"updatedAt":"26/06/2026 12:02:23"}]},{"id":"11468","lat":43.71788587052159,"lon":11.808961629867554,"name":"BIBBIENA-LOC. PIANACCI 8 SS 71","brand":"Q8","address":"LOC. PIANACCI SS 71 8 52011, BIBBIENA, AR","prices":[{"type":"petrol","price":1.809,"self":true,"updatedAt":"26/06/2026 07:45:14"},{"type":"diesel","price":1.889,"self":true,"updatedAt":"26/06/2026 07:45:14"}]},{"id":"7089","lat":43.7309519611638,"lon":11.811676025390625,"name":"C. & C. DISTRIBUZIONE CARBURANTI DI CECCONI E CORDOVANI SNC","brand":"Agip Eni","address":"VIA NAZIONALE  52010, BIBBIENA, AR","prices":[{"type":"petrol","price":1.83,"self":true,"updatedAt":"28/06/2026 00:58:29"},{"type":"diesel","price":1.909,"self":true,"updatedAt":"28/06/2026 00:58:29"}]},{"id":"47427","lat":43.699080381431614,"lon":11.810535159027346,"name":"ESSO BIBBIENA SS.71 Km 179+602","brand":"Esso","address":"SS.71 KM 179+602 BIBBIENA SCALO  51022, BIBBIENA, AR","prices":[{"type":"petrol","price":1.869,"self":true,"updatedAt":"28/06/2026 07:21:56"},{"type":"diesel","price":1.949,"self":true,"updatedAt":"28/06/2026 07:21:56"}]},{"id":"13757","lat":43.698274173742604,"lon":11.810502483317237,"name":"zavagli snc di zavagli gianni e c.","brand":"Agip Eni","address":"VIA UMBRO CASENTINESE  138 52011, BIBBIENA, AR","prices":[{"type":"petrol","price":1.859,"self":true,"updatedAt":"28/06/2026 00:57:17"},{"type":"diesel","price":1.929,"self":true,"updatedAt":"28/06/2026 00:57:17"}]},{"id":"15936","lat":43.565060370919866,"lon":11.862675763376615,"name":"ALFA CARBURANTI","brand":"Aquila","address":"VIA DANTE ALIGHIERI 74/B 52010, CAPOLONA, AR","prices":[{"type":"petrol","price":1.799,"self":true,"updatedAt":"25/06/2026 11:01:57"},{"type":"diesel","price":1.869,"self":true,"updatedAt":"25/06/2026 11:01:57"}]},{"id":"60139","lat":43.61345144757928,"lon":11.995510188072194,"name":"ALA CAPRESE","brand":"Ala","address":"via Fosso da Bagno 38 52033, CAPRESE MICHELANGELO, AR","prices":[{"type":"petrol","price":1.869,"self":true,"updatedAt":"27/06/2026 00:31:57"},{"type":"diesel","price":1.969,"self":true,"updatedAt":"27/06/2026 00:31:57"}]},{"id":"53095","lat":43.662831,"lon":11.840828,"name":"6881","brand":"Tamoil","address":"UMBRO CASENTINESE SNC 52016, CASTEL FOCOGNANO, AR","prices":[{"type":"petrol","price":1.779,"self":true,"updatedAt":"27/06/2026 23:29:53"},{"type":"diesel","price":1.839,"self":true,"updatedAt":"27/06/2026 23:29:53"}]},{"id":"58884","lat":43.63974458786013,"lon":11.837681396362868,"name":"PV 4614","brand":"Agip Eni","address":"S. S. 71 UMBRO CASENTINESE 0 52016, CASTEL FOCOGNANO, AR","prices":[{"type":"petrol","price":1.789,"self":true,"updatedAt":"28/06/2026 00:41:14"},{"type":"diesel","price":1.834,"self":true,"updatedAt":"28/06/2026 00:41:14"}]},{"id":"62119","lat":43.52256163889305,"lon":11.767982750711838,"name":"ALA CASTIGLION FIBOCCHI","brand":"Esso","address":"VIA SETTEPONTI 1/r 52029, CASTIGLION FIBOCCHI, AR","prices":[{"type":"petrol","price":1.839,"self":true,"updatedAt":"28/06/2026 01:34:33"},{"type":"diesel","price":1.919,"self":true,"updatedAt":"28/06/2026 01:34:33"}]},{"id":"58084","lat":43.68121,"lon":11.829635,"name":"55385 CHIUSI DELLA VERNA","brand":"Agip Eni","address":"S.S.71 KM.176+460, LOC.CORSALONE, CHIUSI DELLA VERNA, AR","prices":[{"type":"petrol","price":1.829,"self":true,"updatedAt":"28/06/2026 01:05:46"},{"type":"diesel","price":1.889,"self":true,"updatedAt":"28/06/2026 01:05:46"}]},{"id":"55530","lat":43.693693833367796,"lon":11.938018798828125,"name":"M.P.","brand":"Pompe Bianche","address":"ROMA 47 52010, CHIUSI DELLA VERNA, AR","prices":[{"type":"petrol","price":1.829,"self":true,"updatedAt":"27/06/2026 23:27:14"},{"type":"diesel","price":1.909,"self":true,"updatedAt":"27/06/2026 23:27:14"}]},{"id":"4906","lat":43.7243039955687,"lon":11.77504382837653,"name":"AQUILA - PONTE A POPPI","brand":"Aquila","address":"Statale 70 della Consuma, Km. 35+360, dir. Arezzo - 52014, POPPI, AR","prices":[{"type":"petrol","price":1.799,"self":true,"updatedAt":"24/06/2026 07:19:59"},{"type":"diesel","price":1.889,"self":true,"updatedAt":"24/06/2026 07:19:59"},{"type":"methane","price":1.699,"self":false,"updatedAt":"24/06/2026 07:19:59"},{"type":"lpg","price":0.739,"self":false,"updatedAt":"24/06/2026 07:19:59"}]},{"id":"8260","lat":43.572313836152254,"lon":11.871165351867717,"name":"ARCA SNC DI ARTINI E CACCIALUPI","brand":"Api-Ip","address":"VIA VIA CINTA ESTERNA SR71 52010, SUBBIANO (AR) -224 52010, SUBBIANO, AR","prices":[{"type":"petrol","price":1.789,"self":true,"updatedAt":"23/06/2026 08:17:20"},{"type":"diesel","price":1.854,"self":true,"updatedAt":"23/06/2026 08:17:20"}]},{"id":"62611","lat":43.56058060094855,"lon":11.855900791887647,"name":"DS FUEL CASTELNUOVO","brand":"Pompe Bianche","address":"Località Castelnuovo 69 52010, SUBBIANO, AR","prices":[{"type":"petrol","price":1.783,"self":false,"updatedAt":"22/06/2026 11:18:25"},{"type":"diesel","price":1.844,"self":false,"updatedAt":"22/06/2026 11:18:25"}]},{"id":"62788","lat":43.577585879323685,"lon":11.87093880489349,"name":"DS FUEL Via Verdi Subbiano","brand":"Pompe Bianche","address":"VIa Verdi 74 52010, SUBBIANO, AR","prices":[{"type":"petrol","price":1.783,"self":false,"updatedAt":"22/06/2026 11:17:52"},{"type":"diesel","price":1.844,"self":false,"updatedAt":"22/06/2026 11:17:52"}]}]